{
    "data":[
        {
            "id": 1,
            "name": "大本营",
            "children": [
              {
                "id": 4,
                "name": "市场部",
                "children": [
                  {
                    "id": 7,
                    "name": "飞虎队"
                  },
                  {
                    "id": 8,
                    "name": "雷霆队"
                  },
                  {
                    "id": 9,
                    "name": "星火队"
                  },
                  {
                    "id": 10,
                    "name": "冲锋队"
                  },
                  {
                    "id": 11,
                    "name": "渠道组"
                  },
                  {
                    "id": 12,
                    "name": "政委组"
                  },
                  {
                    "id": 13,
                    "name": "测试001"
                  },
                  {
                    "id": 14,
                    "name": "战狼组"
                  }
                ]
              },
              {
                "id": 2,
                "name": "媒体运营部"
              },
              {
                "id": 3,
                "name": "增值部"
              },
              {
                "id": 5,
                "name": "财务"
              },
              {
                "id": 6,
                "name": "外部渠道"
              }
            ]
          }
    ]
}